pyramid_yosai/__init__.py
pyramid_yosai/forms.py
pyramid_yosai/tweens.py
pyramid_yosai/webregistry.py
pyramid_yosai-0.1.1.dist-info/DESCRIPTION.rst
pyramid_yosai-0.1.1.dist-info/METADATA
pyramid_yosai-0.1.1.dist-info/RECORD
pyramid_yosai-0.1.1.dist-info/WHEEL
pyramid_yosai-0.1.1.dist-info/metadata.json
pyramid_yosai-0.1.1.dist-info/top_level.txt
