Metadata-Version: 2.0
Name: pyramid-yosai
Version: 0.1.1
Summary: pyramid_yosai
Home-page: UNKNOWN
Author: UNKNOWN
Author-email: UNKNOWN
License: UNKNOWN
Keywords: web wsgi pyramid yosai security rbac authorization
Platform: UNKNOWN
Classifier: Programming Language :: Python
Classifier: Framework :: Pyramid
Classifier: Topic :: Internet :: WWW/HTTP
Classifier: Topic :: Internet :: WWW/HTTP :: WSGI :: Application
Requires-Dist: pyramid
Requires-Dist: yosai
